setup.cfg
setup.py
PigKernel/__init__.py
PigKernel/kernel.py
SimplePigKernel.egg-info/PKG-INFO
SimplePigKernel.egg-info/SOURCES.txt
SimplePigKernel.egg-info/dependency_links.txt
SimplePigKernel.egg-info/top_level.txt