Metadata-Version: 1.1
Name: SimplePigKernel
Version: 0.1
Summary: A pig kernel for Jupyter
Home-page: https://github.com/rfestag/SimplePigKernel
Author: Ryan Festag
Author-email: rfestag@gmail.com
License: GPLv3
Download-URL: https://github.com/rfestag/SimplePigKernel/tarball/0.1
Platform: UNKNOWN
